access_azure_keyvault/__init__.py
access_azure_keyvault/__main__.py
access_azure_keyvault/_aak.py
access_azure_keyvault-0.0.6.dist-info/LICENSE
access_azure_keyvault-0.0.6.dist-info/METADATA
access_azure_keyvault-0.0.6.dist-info/WHEEL
access_azure_keyvault-0.0.6.dist-info/top_level.txt
access_azure_keyvault-0.0.6.dist-info/RECORD
