Metadata-Version: 2.1
Name: access-azure-keyvault
Version: 0.0.6
Summary: Simple tool to access secrets in Azure keyvaults
Author-email: Wolfgang Hottgenroth <wolfgang.hottgenroth@icloud.com>
License: MIT License        
Project-URL: Homepage, https://home.hottis.de/gitlab/wolutator/access-azure-keyvault
Project-URL: Bug Tracker, https://home.hottis.de/gitlab/wolutator/access-azure-keyvault/-/issues
Classifier: Programming Language :: Python :: 3
Classifier: License :: OSI Approved :: MIT License
Classifier: Operating System :: OS Independent
Requires-Python: >=3.7
License-File: LICENSE
Requires-Dist: azure.keyvault (>=4.2.0)
Requires-Dist: azure.identity (>=1.10.0)
Requires-Dist: azure.core (>=1.25.1)
Requires-Dist: loguru (>=0.6.0)
